tmdbsimple/__init__.py
tmdbsimple/account.py
tmdbsimple/base.py
tmdbsimple/changes.py
tmdbsimple/configuration.py
tmdbsimple/discover.py
tmdbsimple/find.py
tmdbsimple/genres.py
tmdbsimple/movies.py
tmdbsimple/people.py
tmdbsimple/search.py
tmdbsimple/tv.py
tmdbsimple-2.9.1.dist-info/LICENSE
tmdbsimple-2.9.1.dist-info/METADATA
tmdbsimple-2.9.1.dist-info/WHEEL
tmdbsimple-2.9.1.dist-info/top_level.txt
tmdbsimple-2.9.1.dist-info/RECORD
